This file is a merged representation of a subset of the codebase, containing specifically included files and files not matching ignore patterns, combined into a single document by Repomix.

<file_summary>
This section contains a summary of this file.

<purpose>
This file contains a packed representation of a subset of the repository's contents that is considered the most important context.
It is designed to be easily consumable by AI systems for analysis, code review,
or other automated processes.
</purpose>

<file_format>
The content is organized as follows:
1. This summary section
2. Repository information
3. Directory structure
4. Repository files (if enabled)
5. Multiple file entries, each consisting of:
  - File path as an attribute
  - Full contents of the file
</file_format>

<usage_guidelines>
- This file should be treated as read-only. Any changes should be made to the
  original repository files, not this packed version.
- When processing this file, use the file path to distinguish
  between different files in the repository.
- Be aware that this file may contain sensitive information. Handle it with
  the same level of security as you would the original repository.
</usage_guidelines>

<notes>
- Some files may have been excluded based on .gitignore rules and Repomix's configuration
- Binary files are not included in this packed representation. Please refer to the Repository Structure section for a complete list of file paths, including binary files
- Only files matching these patterns are included: **/src/main/**/*, **/pom.xml, **/build.gradle
- Files matching these patterns are excluded: **/node_modules/**, **/target/**, **/build/**, **/.gradle/**, **/.settings/**, **/.classpath/**, **/.project/**, **/*.iml, **/.idea/**, **/.vscode/**, **/mvnw*, **/.git/**, **/*.log, **/.env*
- Files matching patterns in .gitignore are excluded
- Files matching default ignore patterns are excluded
- Files are sorted by Git change count (files with more changes are at the bottom)
</notes>

</file_summary>

<directory_structure>
pom.xml
src/main/java/com/colegio/reporte_service/client/EstudianteClient.java
src/main/java/com/colegio/reporte_service/client/EvaluacionClient.java
src/main/java/com/colegio/reporte_service/config/SecurityConfig.java
src/main/java/com/colegio/reporte_service/controller/ReporteController.java
src/main/java/com/colegio/reporte_service/dto/ReporteGeneralDto.java
src/main/java/com/colegio/reporte_service/ReporteServiceApplication.java
src/main/java/com/colegio/reporte_service/security/JwtConfig.java
src/main/java/com/colegio/reporte_service/security/JwtTokenFilter.java
src/main/java/com/colegio/reporte_service/service/ReporteService.java
src/main/resources/application.yml
src/main/resources/bootstrap.yml
</directory_structure>

<files>
This section contains the contents of the repository's files.

<file path="pom.xml">
<?xml version="1.0" encoding="UTF-8"?>
<project xmlns="http://maven.apache.org/POM/4.0.0" xmlns:xsi="http://www.w3.org/2001/XMLSchema-instance"
         xsi:schemaLocation="http://maven.apache.org/POM/4.0.0 https://maven.apache.org/xsd/maven-4.0.0.xsd">
    <modelVersion>4.0.0</modelVersion>
    <parent>
        <groupId>org.springframework.boot</groupId>
        <artifactId>spring-boot-starter-parent</artifactId>
        <version>3.2.5</version>
        <relativePath/>
    </parent>
    <groupId>com.colegio</groupId>
    <artifactId>reporte-service</artifactId>
    <version>0.0.1-SNAPSHOT</version>
    <name>reporte-service</name>
    <description>Microservicio de Reportes y Estadísticas</description>
    <properties>
        <java.version>21</java.version>
        <spring-cloud.version>2023.0.1</spring-cloud.version>
    </properties>
    <dependencies>
        <dependency>
			<groupId>org.springframework.cloud</groupId>
			<artifactId>spring-cloud-starter-bootstrap</artifactId>
		</dependency>
		<dependency>
			<groupId>io.jsonwebtoken</groupId>
			<artifactId>jjwt-api</artifactId>
			<version>0.11.5</version>
		</dependency>
		<dependency>
			<groupId>io.jsonwebtoken</groupId>
			<artifactId>jjwt-impl</artifactId>
			<version>0.11.5</version>
			<scope>runtime</scope>
		</dependency>
		<dependency>
			<groupId>io.jsonwebtoken</groupId>
			<artifactId>jjwt-jackson</artifactId>
			<version>0.11.5</version>
			<scope>runtime</scope>
		</dependency>
		<dependency>
			<groupId>org.springframework.boot</groupId>
			<artifactId>spring-boot-starter-security</artifactId>
		</dependency>
        <dependency>
            <groupId>org.springframework.boot</groupId>
            <artifactId>spring-boot-starter-web</artifactId>
        </dependency>
        <dependency>
            <groupId>org.springframework.cloud</groupId>
            <artifactId>spring-cloud-starter-config</artifactId>
        </dependency>
        <dependency>
            <groupId>org.springframework.cloud</groupId>
            <artifactId>spring-cloud-starter-netflix-eureka-client</artifactId>
        </dependency>
        <dependency>
            <groupId>org.springframework.cloud</groupId>
            <artifactId>spring-cloud-starter-openfeign</artifactId>
        </dependency>
        <dependency>
            <groupId>org.springdoc</groupId>
            <artifactId>springdoc-openapi-starter-webmvc-ui</artifactId>
            <version>2.5.0</version>
        </dependency>
        <dependency>
            <groupId>org.springframework.boot</groupId>
            <artifactId>spring-boot-starter-test</artifactId>
            <scope>test</scope>
        </dependency>
    </dependencies>
    <dependencyManagement>
        <dependencies>
            <dependency>
                <groupId>org.springframework.cloud</groupId>
                <artifactId>spring-cloud-dependencies</artifactId>
                <version>${spring-cloud.version}</version>
                <type>pom</type>
                <scope>import</scope>
            </dependency>
        </dependencies>
    </dependencyManagement>
    <build>
        <plugins>
            <plugin>
                <groupId>org.springframework.boot</groupId>
                <artifactId>spring-boot-maven-plugin</artifactId>
            </plugin>
            <plugin>
                <groupId>org.apache.maven.plugins</groupId>
                <artifactId>maven-surefire-plugin</artifactId>
                <configuration>
                    <argLine>@{argLine} -Dnet.bytebuddy.experimental=true</argLine>
                </configuration>
            </plugin>
            <plugin>
                <groupId>org.jacoco</groupId>
                <artifactId>jacoco-maven-plugin</artifactId>
                <version>0.8.11</version>
                <configuration>
                    <excludes>
                        <exclude>com/colegio/reporte_service/dto/**</exclude>
                        <exclude>com/colegio/reporte_service/client/**</exclude>
                        <exclude>com/colegio/reporte_service/ReporteServiceApplication.class</exclude>
                    </excludes>
                </configuration>
                <executions>
                    <execution>
                        <goals><goal>prepare-agent</goal></goals>
                    </execution>
                    <execution>
                        <id>report</id>
                        <phase>test</phase>
                        <goals><goal>report</goal></goals>
                    </execution>
                </executions>
            </plugin>
        </plugins>
    </build>
</project>
</file>

<file path="src/main/java/com/colegio/reporte_service/client/EstudianteClient.java">
package com.colegio.reporte_service.client;

import org.springframework.cloud.openfeign.FeignClient;
import org.springframework.web.bind.annotation.GetMapping;
import java.util.List;

@FeignClient(name = "estudiante-service", path = "/api/estudiantes")
public interface EstudianteClient {

    @GetMapping
    List<Object> listarTodos();
}
</file>

<file path="src/main/java/com/colegio/reporte_service/client/EvaluacionClient.java">
package com.colegio.reporte_service.client;

import org.springframework.cloud.openfeign.FeignClient;
import org.springframework.web.bind.annotation.GetMapping;
import java.util.List;
import java.util.Map;

@FeignClient(name = "evaluacion-service", path = "/api/evaluaciones")
public interface EvaluacionClient {

    @GetMapping
    List<Map<String, Object>> listarTodas();
}
</file>

<file path="src/main/java/com/colegio/reporte_service/config/SecurityConfig.java">
package com.colegio.reporte_service.config;

import com.colegio.reporte_service.security.JwtTokenFilter;
import org.springframework.beans.factory.annotation.Autowired;
import org.springframework.context.annotation.Bean;
import org.springframework.context.annotation.Configuration;
import org.springframework.security.config.annotation.web.builders.HttpSecurity;
import org.springframework.security.web.SecurityFilterChain;
import org.springframework.security.web.authentication.UsernamePasswordAuthenticationFilter;

@Configuration
public class SecurityConfig {

    @Autowired
    private JwtTokenFilter jwtTokenFilter;

    @Bean
    public SecurityFilterChain filterChain(HttpSecurity http) throws Exception {
        http
                .csrf(csrf -> csrf.disable())
                .cors(cors -> cors.disable())
                .authorizeHttpRequests(auth -> auth
                        .requestMatchers(
                                "/v3/api-docs/**",
                                "/swagger-ui/**",
                                "/swagger-ui.html"
                        ).permitAll()
                        .anyRequest().authenticated()
                )
                .addFilterBefore(jwtTokenFilter, UsernamePasswordAuthenticationFilter.class)
                .httpBasic(httpBasic -> httpBasic.disable())
                .formLogin(form -> form.disable());

        return http.build();
    }
}
</file>

<file path="src/main/java/com/colegio/reporte_service/controller/ReporteController.java">
package com.colegio.reporte_service.controller;

import com.colegio.reporte_service.dto.ReporteGeneralDto;
import com.colegio.reporte_service.service.ReporteService;
import io.swagger.v3.oas.annotations.Operation;
import io.swagger.v3.oas.annotations.tags.Tag;
import org.springframework.beans.factory.annotation.Autowired;
import org.springframework.http.ResponseEntity;
import org.springframework.web.bind.annotation.*;

/**
 * Controlador REST que expone endpoints para la generación de reportes y estadísticas.
 * Actúa como un punto de acceso único para la consulta de información consolidada del colegio.
 */
@RestController
@RequestMapping("/api/reportes")
@Tag(name = "Generador de Reportes", description = "Endpoints para la consolidación de estadísticas del colegio")
public class ReporteController {

    @Autowired
    private ReporteService reporteService;

    /**
     * Endpoint para obtener el boletín general consolidado del colegio.
     * @return ResponseEntity con el objeto ReporteGeneralDto y código HTTP 200 (OK).
     */
    @Operation(summary = "Obtener Boletín General", description = "Consulta a múltiples microservicios para armar un informe general del colegio")
    @GetMapping("/general")
    public ResponseEntity<ReporteGeneralDto> obtenerReporteGeneral() {
        return ResponseEntity.ok(reporteService.obtenerReporteGeneral());
    }
}
</file>

<file path="src/main/java/com/colegio/reporte_service/dto/ReporteGeneralDto.java">
package com.colegio.reporte_service.dto;

import io.swagger.v3.oas.annotations.media.Schema;

@Schema(description = "Resumen estadístico general del establecimiento")
public class ReporteGeneralDto {

    @Schema(description = "Cantidad total de alumnos matriculados", example = "450")
    private Integer totalEstudiantes;

    @Schema(description = "Promedio de notas a nivel institucional", example = "5.8")
    private Double promedioGeneralColegio;

    @Schema(description = "Porcentaje de asistencia diaria", example = "92%")
    private String asistenciaPromedio;

    @Schema(description = "Mensaje informativo del sistema", example = "Operativo")
    private String estado;

    public ReporteGeneralDto(Integer totalEstudiantes, Double promedioGeneralColegio, String asistenciaPromedio, String estado) {
        this.totalEstudiantes = totalEstudiantes;
        this.promedioGeneralColegio = promedioGeneralColegio;
        this.asistenciaPromedio = asistenciaPromedio;
        this.estado = estado;
    }

    // Getters
    public Integer getTotalEstudiantes() { return totalEstudiantes; }
    public Double getPromedioGeneralColegio() { return promedioGeneralColegio; }
    public String getAsistenciaPromedio() { return asistenciaPromedio; }
    public String getEstado() { return estado; }
}
</file>

<file path="src/main/java/com/colegio/reporte_service/ReporteServiceApplication.java">
package com.colegio.reporte_service;

import org.springframework.boot.SpringApplication;
import org.springframework.boot.autoconfigure.SpringBootApplication;
import org.springframework.cloud.client.discovery.EnableDiscoveryClient;
import org.springframework.cloud.openfeign.EnableFeignClients;

@SpringBootApplication
@EnableDiscoveryClient
@EnableFeignClients
public class ReporteServiceApplication {
	public static void main(String[] args) {
		SpringApplication.run(ReporteServiceApplication.class, args);
	}
}
</file>

<file path="src/main/java/com/colegio/reporte_service/security/JwtConfig.java">
package com.colegio.reporte_service.security;

import org.springframework.beans.factory.annotation.Value;
import org.springframework.context.annotation.Configuration;

@Configuration
public class JwtConfig {
    @Value("${jwt.secret}")
    private String secret;

    public String getSecret() {
        return secret;
    }
}
</file>

<file path="src/main/java/com/colegio/reporte_service/security/JwtTokenFilter.java">
package com.colegio.reporte_service.security;

import io.jsonwebtoken.Claims;
import io.jsonwebtoken.Jwts;
import io.jsonwebtoken.security.Keys;
import jakarta.servlet.FilterChain;
import jakarta.servlet.ServletException;
import jakarta.servlet.http.HttpServletRequest;
import jakarta.servlet.http.HttpServletResponse;
import org.springframework.beans.factory.annotation.Autowired; 
import org.springframework.http.HttpHeaders;
import org.springframework.security.authentication.UsernamePasswordAuthenticationToken;
import org.springframework.security.core.authority.SimpleGrantedAuthority;
import org.springframework.security.core.context.SecurityContextHolder;
import org.springframework.stereotype.Component;
import org.springframework.web.filter.OncePerRequestFilter;
import java.io.IOException;
import java.util.Collections;

@Component
public class JwtTokenFilter extends OncePerRequestFilter {

    @Autowired
    private JwtConfig jwtConfig; 

    @Override
    protected void doFilterInternal(HttpServletRequest request, HttpServletResponse response, FilterChain filterChain) throws ServletException, IOException {
        String authHeader = request.getHeader(HttpHeaders.AUTHORIZATION);

        if (authHeader != null && authHeader.startsWith("Bearer ")) {
            String token = authHeader.substring(7);
            try {
                Claims claims = Jwts.parserBuilder()
                        .setSigningKey(Keys.hmacShaKeyFor(jwtConfig.getSecret().getBytes()))
                        .build()
                        .parseClaimsJws(token)
                        .getBody();

                String username = claims.getSubject();
                String rol = claims.get("rol", String.class);

                UsernamePasswordAuthenticationToken auth = new UsernamePasswordAuthenticationToken(
                        username, null, Collections.singletonList(new SimpleGrantedAuthority("ROLE_" + rol))
                );

                SecurityContextHolder.getContext().setAuthentication(auth);
            } catch (Exception e) {
                SecurityContextHolder.clearContext();
            }
        }
        filterChain.doFilter(request, response);
    }
}
</file>

<file path="src/main/java/com/colegio/reporte_service/service/ReporteService.java">
package com.colegio.reporte_service.service;

import com.colegio.reporte_service.client.EstudianteClient;
import com.colegio.reporte_service.client.EvaluacionClient;
import com.colegio.reporte_service.dto.ReporteGeneralDto;
import org.springframework.beans.factory.annotation.Autowired;
import org.springframework.stereotype.Service;
import java.util.List;
import java.util.Map;

/**
 * Servicio orquestador (patrón Backend For Frontend - BFF) que consolida información de diferentes microservicios.
 * Se comunica con estudiante-service y evaluacion-service mediante Feign Clients para generar
 * reportes y estadísticas globales de la institución.
 */
@Service
public class ReporteService {

    @Autowired
    private EstudianteClient estudianteClient;

    @Autowired
    private EvaluacionClient evaluacionClient;

    /**
     * Genera un reporte general del colegio consolidando datos de matrícula y calificaciones.
     * Maneja excepciones de comunicación de forma controlada proporcionando estados y valores por defecto
     * si algún microservicio dependiente no responde.
     * @return Objeto ReporteGeneralDto con el total de estudiantes, el promedio general y el estado de la operación.
     */
    public ReporteGeneralDto obtenerReporteGeneral() {
        int totalReal = 0;
        double promedioReal = 0.0;
        String mensajeEstado = "Reporte BFF sincronizado con Estudiantes y Notas \uD83D\uDE80";

        // 1. Llamar a Estudiantes
        try {
            List<Object> estudiantes = estudianteClient.listarTodos();
            totalReal = estudiantes.size();
        } catch (Exception e) {
            mensajeEstado = "Aviso: Estudiante-Service no responde.";
        }

        // 2. Llamar a Evaluaciones y calcular promedio
        try {
            List<Map<String, Object>> notas = evaluacionClient.listarTodas();
            if (!notas.isEmpty()) {
                double suma = 0.0;
                for (Map<String, Object> notaObj : notas) {
                    // Extraemos la nota del JSON que nos responde el otro microservicio
                    suma += Double.parseDouble(notaObj.get("nota").toString());
                }
                // Calculamos el promedio y lo redondeamos a 1 decimal
                promedioReal = Math.round((suma / notas.size()) * 10.0) / 10.0;
            }
        } catch (Exception e) {
            mensajeEstado = "Aviso: Evaluacion-Service no responde. Promedio en 0.";
        }

        return new ReporteGeneralDto(
                totalReal,
                promedioReal,
                "92%",
                mensajeEstado
        );
    }
}
</file>

<file path="src/main/resources/application.yml">
# Propiedades locales del microservicio

jwt:
  secret: 404E635266556A586E3272357538782F413F4428472B4B6250645367566B5970
</file>

<file path="src/main/resources/bootstrap.yml">
spring:
  application:
    name: reporte-service
  cloud:
    config:
      uri: http://config-server:8888
      fail-fast: true
</file>

</files>
